{
  "unversionedId": "Alsys Connect/Induction",
  "id": "Alsys Connect/Induction",
  "title": "Induction",
  "description": "What is the Induction section?",
  "source": "@site/docs/Alsys Connect/Induction.md",
  "sourceDirName": "Alsys Connect",
  "slug": "/Alsys Connect/Induction",
  "permalink": "/alsys-user-playbook/next/Alsys Connect/Induction",
  "draft": false,
  "tags": [],
  "version": "current",
  "sidebarPosition": 6,
  "frontMatter": {
    "sidebar_position": 6
  },
  "sidebar": "tutorialSidebar",
  "previous": {
    "title": "Health",
    "permalink": "/alsys-user-playbook/next/Alsys Connect/Health"
  },
  "next": {
    "title": "Newsfeed",
    "permalink": "/alsys-user-playbook/next/Alsys Connect/Newsfeed"
  }
}